tabuletta/__init__.py
tabuletta/tabuletta.py
tabuletta-0.2.2.dist-info/METADATA
tabuletta-0.2.2.dist-info/WHEEL
tabuletta-0.2.2.dist-info/top_level.txt
tabuletta-0.2.2.dist-info/RECORD
