Metadata-Version: 2.1
Name: tabuletta
Version: 0.2.2
